sclog/__init__.py
sclog/sclog.py
sclog-0.1.2.dist-info/LICENSE
sclog-0.1.2.dist-info/WHEEL
sclog-0.1.2.dist-info/METADATA
sclog-0.1.2.dist-info/RECORD
