Metadata-Version: 2.1
Name: sclog
Version: 0.1.2
Summary: simple colorized log
Home-page: https://github.com/nmalkin/sclog
License: BSD-3-Clause
Author: nmalkin
Requires-Python: >=3.5
Classifier: License :: OSI Approved :: BSD License
Classifier: Programming Language :: Python :: 3
Classifier: Programming Language :: Python :: 3.5
Classifier: Programming Language :: Python :: 3.6
Classifier: Programming Language :: Python :: 3.7
Classifier: Programming Language :: Python :: 3.8
Classifier: Programming Language :: Python :: 3.9
Provides-Extra: color
Requires-Dist: colorlog (>=4.6.2,<5.0.0); extra == "color"
